mrproject/__init__.py
mrproject/__main__.py
mrproject/list.py
mrproject/new.py
mrproject/py.typed
mrproject/templates/default/MRPROJECT_PROJECT_NAME/.gitignore
mrproject/templates/default/MRPROJECT_PROJECT_NAME/.pre-commit-config.yaml
mrproject/templates/default/MRPROJECT_PROJECT_NAME/LICENSE
mrproject/templates/default/MRPROJECT_PROJECT_NAME/MRPROJECT_PROJECT_NAME/__init__.py
mrproject/templates/default/MRPROJECT_PROJECT_NAME/MRPROJECT_PROJECT_NAME/py.typed
mrproject/templates/default/MRPROJECT_PROJECT_NAME/MRPROJECT_PROJECT_NAME/utils.py
mrproject/templates/default/MRPROJECT_PROJECT_NAME/README.md
mrproject/templates/default/MRPROJECT_PROJECT_NAME/docs/api/utils.md
mrproject/templates/default/MRPROJECT_PROJECT_NAME/docs/index.md
mrproject/templates/default/MRPROJECT_PROJECT_NAME/mkdocs.yml
mrproject/templates/default/MRPROJECT_PROJECT_NAME/poetry.lock
mrproject/templates/default/MRPROJECT_PROJECT_NAME/pyproject.toml
mrproject/templates/default/MRPROJECT_PROJECT_NAME/tests/test_utils.py
mrproject/templates/default/README.md
mrproject/templates/default/mrproject_template.toml
mrproject/utils.py
mrproject-0.2.0.dist-info/LICENSE
mrproject-0.2.0.dist-info/METADATA
mrproject-0.2.0.dist-info/WHEEL
mrproject-0.2.0.dist-info/entry_points.txt
mrproject-0.2.0.dist-info/RECORD
