Metadata-Version: 2.1
Name: mrproject
Version: 0.2.0
Summary: `mrproject` - make projects from templates
Home-page: https://github.com/sotte/mrproject/
License: MIT
Keywords: mrproject,template,scaffold
Author: Stefan Otte
Author-email: stefan.otte@gmail.com
Requires-Python: >=3.11,<4.0
Classifier: License :: OSI Approved :: MIT License
Classifier: Programming Language :: Python :: 3
Classifier: Programming Language :: Python :: 3.11
Classifier: Programming Language :: Python :: 3.12
Requires-Dist: appeal (>=0.6.2)
Requires-Dist: platformdirs (>=4.1.0)
Requires-Dist: rich (>=13.7.0)
Requires-Dist: tomli (>=2.0.1)
